{
  "version": "0.3.14-fixed",
  "steps": [
    {
      "tag": "CreateField",
      "model": "ReportComment",
      "field": "writer",
      "type": "User",
      "arity": "Required"
    },
    {
      "tag": "CreateDirective",
      "location": {
        "path": {
          "tag": "Field",
          "model": "ReportComment",
          "field": "writer"
        },
        "directive": "relation"
      }
    },
    {
      "tag": "CreateArgument",
      "location": {
        "tag": "Directive",
        "path": {
          "tag": "Field",
          "model": "ReportComment",
          "field": "writer"
        },
        "directive": "relation"
      },
      "argument": "fields",
      "value": "[writerId]"
    },
    {
      "tag": "CreateArgument",
      "location": {
        "tag": "Directive",
        "path": {
          "tag": "Field",
          "model": "ReportComment",
          "field": "writer"
        },
        "directive": "relation"
      },
      "argument": "references",
      "value": "[id]"
    },
    {
      "tag": "CreateField",
      "model": "ReportComment",
      "field": "writerId",
      "type": "String",
      "arity": "Required"
    }
  ]
}